{
  "$schema": "https://mintlify.com/docs.json",
  "name": "Praetorius",
  "theme": "palm",
  "colors": {
    "primary": "#6366f1",
    "light": "#818cf8",
    "dark": "#4f46e5"
  },
  "navbar": {
    "primary": {
      "type": "github",
      "href": "https://github.com/cbassuarez/praetorius"
    }
  },
  "footer": {
    "socials": {
      "github": "https://github.com/cbassuarez/praetorius"
    }
  },
  "navigation": {
    "tabs": [
      {
        "tab": "Documentation",
        "groups": [
          {
            "group": "Getting Started",
            "pages": [
              "introduction",
              "installation",
              "quickstart"
            ]
          },
          {
            "group": "Core Concepts",
            "pages": [
              "concepts/works-data",
              "concepts/page-follow",
              "concepts/skins"
            ]
          },
          {
            "group": "Guides",
            "pages": [
              "guides/adding-works",
              "guides/generating-output",
              "guides/embedding",
              "guides/squarespace-integration",
              "guides/data-import-export"
            ]
          },
          {
            "group": "Configuration",
            "pages": [
              "configuration/works-json",
              "configuration/score-mapping",
              "configuration/deep-linking"
            ]
          }
        ]
      },
      {
        "tab": "CLI Reference",
        "groups": [
          {
            "group": "Commands",
            "pages": [
              "cli/init",
              "cli/add",
              "cli/edit",
              "cli/remove",
              "cli/list",
              "cli/order",
              "cli/generate",
              "cli/import",
              "cli/export",
              "cli/validate",
              "cli/preview",
              "cli/docs",
              "cli/doctor"
            ]
          },
          {
            "group": "Skins",
            "pages": [
              "skins/overview",
              "skins/console",
              "skins/vite-breeze",
              "skins/typefolio",
              "skins/cards-tabs",
              "skins/docs-reader",
              "skins/kiosk",
              "skins/typescatter"
            ]
          }
        ]
      },
      {
        "tab": "Resources",
        "groups": [
          {
            "group": "Help",
            "pages": [
              "troubleshooting",
              "faq",
              "contributing"
            ]
          }
        ]
      }
    ]
  }
}
